nonebot_plugin_who_at_me/__init__.py
nonebot_plugin_who_at_me/config.py
nonebot_plugin_who_at_me/data_source.py
nonebot_plugin_who_at_me/database.py
nonebot_plugin_who_at_me/rule.py
nonebot_plugin_who_at_me/utils.py
nonebot_plugin_whoatme_xqs-0.1.0.dist-info/LICENSE
nonebot_plugin_whoatme_xqs-0.1.0.dist-info/METADATA
nonebot_plugin_whoatme_xqs-0.1.0.dist-info/WHEEL
nonebot_plugin_whoatme_xqs-0.1.0.dist-info/entry_points.txt
nonebot_plugin_whoatme_xqs-0.1.0.dist-info/top_level.txt
nonebot_plugin_whoatme_xqs-0.1.0.dist-info/RECORD
