Metadata-Version: 2.2
Name: nonebot-plugin-whoatme-xqs
Version: 0.1.0
Classifier: Programming Language :: Python :: 3
Classifier: License :: OSI Approved :: MIT License
Classifier: Operating System :: OS Independent
Requires-Python: >=3.7
License-File: LICENSE
Requires-Dist: nonebot2
Requires-Dist: nonebot-adapter-onebot
Requires-Dist: pydantic
Requires-Dist: peewee
Requires-Dist: aiohttp
Dynamic: classifier
Dynamic: requires-dist
Dynamic: requires-python
